lldb_dfsan.py
lldb_dfsan-0.1.1.dist-info/LICENSE
lldb_dfsan-0.1.1.dist-info/METADATA
lldb_dfsan-0.1.1.dist-info/WHEEL
lldb_dfsan-0.1.1.dist-info/top_level.txt
lldb_dfsan-0.1.1.dist-info/RECORD
