Metadata-Version: 2.1
Name: lldb-dfsan
Version: 0.1.1
Summary: LLDB plugin for debugging DFSan'd binaries.
Author-email: Raphael Isemann <teemperor@gmail.com>
Project-URL: Homepage, https://github.com/vusec/lldb-dfsan
Project-URL: Bug Tracker, https://github.com/vusec/lldb-dfsan/issues
Classifier: Programming Language :: Python :: 3
Classifier: License :: OSI Approved :: Apache Software License
Classifier: Operating System :: POSIX :: Linux
Classifier: Topic :: Software Development :: Debuggers
Requires-Python: >=3.7
License-File: LICENSE
